[
    {  
        "_id": {
            "$oid": "657123196e3760c396e69ef4"     
        },
        "username": "Kaneki",
        "password": "12345",
        "profileimg": "/assets/img/kaneki.jpg",
        "membership": "Platinum",
        "folders": [
            {
                "_id": {
                    "$oid": "6571240b6e3760c396e69ef8"     
                }
            },
            {
                "_id": {
                    "$oid": "6571240b6e3760c396e69ef9"     
                }
            },
            {
                "_id": {
                    "$oid": "6571240b6e3760c396e69efa"     
                }
            },
            {
                "_id": {
                    "$oid": "657152926e3760c396e69f08"     
                }
            },
            {
                "_id": {
                    "$oid": "657152926e3760c396e69f09"     
                }
            }, 
            {
                "_id": {
                    "$oid": "657152926e3760c396e69f0a"     
                }
            },
            {
                "_id": {
                    "$oid": "657152926e3760c396e69f0b"     
                }
            },
            {
                "_id": {
                    "$oid": "657152926e3760c396e69f0c"     
                }
            },
            {
                "_id": {
                    "$oid": "657152926e3760c396e69f0d"     
                }
            },
            {
                "_id": {
                    "$oid": "657152926e3760c396e69f0e"     
                }
            }  
        ]
    },
    { 
        "_id": {
            "$oid": "657146d36e3760c396e69f02"     
        },
        "username": "Sinon",
        "password": "12345",
        "profileimg": "/assets/img/sinon.jpg",
        "membership": "Premium",
        "folders": [
            {
                "_id": {
                    "$oid": "657152926e3760c396e69f0f"     
                }
            },
            {
                "_id": {
                    "$oid": "657152926e3760c396e69f10"     
                }
            },
            {
                "_id": {
                    "$oid": "657152926e3760c396e69f11"     
                }
            },
            {
                "_id": {
                    "$oid": "657152926e3760c396e69f12"     
                }
            },
            {
                "_id": {
                    "$oid": "657152926e3760c396e69f13"     
                }
            }  
        ]
    },
    {  
        "_id": {
            "$oid": "657146d36e3760c396e69f03"     
        },
        "username": "Toshiro",
        "password": "12345",
        "profileimg": "/assets/img/hitsugaya.jpg",
        "membership": "Standard",
        "folders": [
            {
                "_id": {
                    "$oid": "657152926e3760c396e69f14"     
                }
            },
            {
                "_id": {
                    "$oid": "657152926e3760c396e69f15"     
                }
            },
            {
                "_id": {
                    "$oid": "657152926e3760c396e69f16"     
                }
            }
        ]
    },
    {  
        "_id": {
            "$oid": "657146d36e3760c396e69f04"     
        },
        "username": "Raphtalia",
        "password": "12345",
        "profileimg": "/assets/img/raphtalia.jpg",
        "membership": "Free",
        "folders": [
            {
                "_id": {
                    "$oid": "657152926e3760c396e69f17"     
                }
            },
            {
                "_id": {
                    "$oid": "657152926e3760c396e69f18"     
                }
            }
        ]
    }
]